datahorse/__init__.py
datahorse/__version__.py
datahorse/core.py
datahorse/logger.py
datahorse-0.1.4.dist-info/LICENSE
datahorse-0.1.4.dist-info/METADATA
datahorse-0.1.4.dist-info/WHEEL
datahorse-0.1.4.dist-info/top_level.txt
datahorse-0.1.4.dist-info/RECORD
