Metadata-Version: 2.1
Name: datahorse
Version: 0.1.4
Summary: Your Data Assistant
Home-page: https://datahorse.ai
Author: DeDolphins
Author-email: info@datahorse.ai
License: creativeml-openrail-m
Classifier: Development Status :: 3 - Alpha
Classifier: Intended Audience :: Developers
Classifier: Natural Language :: English
Classifier: Programming Language :: Python
Classifier: Programming Language :: Python :: 3
Classifier: Programming Language :: Python :: 3.7
Classifier: Programming Language :: Python :: 3.8
Classifier: Programming Language :: Python :: 3.9
Classifier: Programming Language :: Python :: 3.10
Requires-Python: >=3.7.0
License-File: LICENSE
Requires-Dist: pandas
Requires-Dist: groq
Requires-Dist: matplotlib
Requires-Dist: seaborn
Requires-Dist: scikit-learn
Provides-Extra: test
Requires-Dist: black ; extra == 'test'
Requires-Dist: coverage ; extra == 'test'
Requires-Dist: flake8 ; extra == 'test'
Requires-Dist: mock ; extra == 'test'
Requires-Dist: pydocstyle ; extra == 'test'
Requires-Dist: pytest ; extra == 'test'
Requires-Dist: pytest-cov ; extra == 'test'
Requires-Dist: tox ; extra == 'test'
